README.rst
setup.py
txroutes/__init__.py
txroutes/__init__.pyc
txroutes.egg-info/PKG-INFO
txroutes.egg-info/SOURCES.txt
txroutes.egg-info/dependency_links.txt
txroutes.egg-info/requires.txt
txroutes.egg-info/top_level.txt